Docs2KG/__init__.py
Docs2KG/cli.py
Docs2KG/agents/__init__.py
Docs2KG/agents/base.py
Docs2KG/agents/cloud.py
Docs2KG/agents/exceptions.py
Docs2KG/agents/hf.py
Docs2KG/agents/manager.py
Docs2KG/agents/ollama.py
Docs2KG/agents/quantization.py
Docs2KG/agents/func/__init__.py
Docs2KG/agents/func/ner_llm_judge.py
Docs2KG/digitization/__init__.py
Docs2KG/digitization/base.py
Docs2KG/digitization/image/__init__.py
Docs2KG/digitization/image/pdf_docling.py
Docs2KG/digitization/native/__init__.py
Docs2KG/digitization/native/ebook.py
Docs2KG/digitization/native/html_parser.py
Docs2KG/digitization/native/word_docling.py
Docs2KG/kg_construction/__init__.py
Docs2KG/kg_construction/base.py
Docs2KG/kg_construction/layout_kg/__init__.py
Docs2KG/kg_construction/layout_kg/layout_kg.py
Docs2KG/kg_construction/metadata_kg/__init__.py
Docs2KG/kg_construction/metadata_kg/metadata_kg.py
Docs2KG/kg_construction/semantic_kg/__init__.py
Docs2KG/kg_construction/semantic_kg/base.py
Docs2KG/kg_construction/semantic_kg/ner/__init__.py
Docs2KG/kg_construction/semantic_kg/ner/ner_prompt_based.py
Docs2KG/kg_construction/semantic_kg/ner/ner_spacy_match.py
Docs2KG/kg_construction/semantic_kg/ontology/__init__.py
Docs2KG/kg_construction/semantic_kg/ontology/entity_type_llm.py
Docs2KG/utils/__init__.py
Docs2KG/utils/config.py
Docs2KG/utils/constants.py
Docs2KG/utils/empty_check.py
Docs2KG/utils/models.py
Docs2KG/utils/neo4j_loader.py
Docs2KG/utils/timer.py
examples/__init__.py
tests/__init__.py
Docs2KG-0.3.5.dist-info/LICENSE
Docs2KG-0.3.5.dist-info/METADATA
Docs2KG-0.3.5.dist-info/WHEEL
Docs2KG-0.3.5.dist-info/entry_points.txt
Docs2KG-0.3.5.dist-info/top_level.txt
Docs2KG-0.3.5.dist-info/RECORD
