Metadata-Version: 2.2
Name: Docs2KG
Version: 0.3.5
Summary: Unified Knowledge Graph Construction from Heterogeneous Documents Assisted by Large Language Models
Home-page: https://docs2kg.ai4wa.com
Author: AI4WA
Author-email: admin@ai4wa.com
Project-URL: Source, https://github.com/AI4WA/Docs2KG
Classifier: Development Status :: 3 - Alpha
Classifier: Intended Audience :: Developers
Classifier: Intended Audience :: Science/Research
Classifier: License :: OSI Approved :: GNU Lesser General Public License v3 (LGPLv3)
Classifier: Topic :: Scientific/Engineering :: Artificial Intelligence
Classifier: Programming Language :: Python :: 3.8
Classifier: Programming Language :: Python :: 3.9
Classifier: Programming Language :: Python :: 3.10
Requires-Python: >=3.8
License-File: LICENSE
Requires-Dist: pandas==2.2.3
Requires-Dist: markdownify==0.14.1
Requires-Dist: beautifulsoup4==4.12.3
Requires-Dist: requests==2.32.3
Requires-Dist: openai==1.58.1
Requires-Dist: tqdm==4.67.1
Requires-Dist: tiktoken==0.8.0
Requires-Dist: transformers==4.47.1
Requires-Dist: torch==2.5.1
Requires-Dist: sentence-transformers==3.3.1
Requires-Dist: loguru==0.7.3
Requires-Dist: llama-cpp-python==0.3.5
Requires-Dist: docling==2.14.0
Requires-Dist: mammoth==1.9.0
Requires-Dist: markdownify==0.14.1
Requires-Dist: ebooklib==0.18
Requires-Dist: html2text==2024.2.26
Requires-Dist: beautifulsoup4==4.12.3
Requires-Dist: spacy==3.8.3
Requires-Dist: markdown==3.7
Requires-Dist: neo4j==5.27.0
Dynamic: author
Dynamic: author-email
Dynamic: classifier
Dynamic: description
Dynamic: description-content-type
Dynamic: home-page
Dynamic: project-url
Dynamic: requires-dist
Dynamic: requires-python
Dynamic: summary
